wheat/__init__.py
wheat/__main__.py
wheat/__version__.py
wheat/calendar/__init__.py
wheat/calendar/attendee.py
wheat/calendar/calendar.py
wheat/calendar/client_credentials/credentials.json
wheat/calendar/event.py
wheat/calendar/google.py
wheat/console/__init__.py
wheat/console/application.py
wheat/console/command_loader.py
wheat/console/commands/__init__.py
wheat/console/commands/about.py
wheat/console/commands/auth.py
wheat/console/commands/command.py
wheat/console/commands/log.py
wheat/console/commands/meeting/__init__.py
wheat/console/commands/meeting/join.py
wheat/console/commands/meeting/peek.py
wheat/console/commands/tag.py
wheat/console/commands/task/__init__.py
wheat/console/commands/task/activate.py
wheat/console/commands/task/list.py
wheat/console/commands/task/sleep.py
wheat/console/commands/view.py
wheat/factory.py
wheat/harvest/__init__.py
wheat/harvest/harvest.py
wheat/harvest/harvest_client.py
wheat/harvest/projects/__init__.py
wheat/harvest/projects/project.py
wheat/harvest/projects/projects.py
wheat/harvest/projects/task.py
wheat/harvest/time_entry.py
wheat/harvest/timesheet.py
wheat/locations.py
wheat/utils/__init__.py
wheat/utils/appdirs.py
wheat/utils/hash.py
wheat/utils/time.py
wheat/utils/yaml_file.py
wheat/utils/zoom.py
wheat-0.9.5.dist-info/entry_points.txt
wheat-0.9.5.dist-info/LICENSE
wheat-0.9.5.dist-info/WHEEL
wheat-0.9.5.dist-info/METADATA
wheat-0.9.5.dist-info/RECORD
